{
    "AX": {
        "error": 0.00798672413007762, 
        "filter_outliers_dict": {
            "filter_outliers": true, 
            "iterations": 1, 
            "std_devs": 2
        }, 
        "fit": "average", 
        "value": -0.08695226281130736
    }, 
    "CDD": {
        "error": 3.827367171126056e-05, 
        "filter_outliers_dict": {
            "filter_outliers": true, 
            "iterations": 1, 
            "std_devs": 10
        }, 
        "fit": "average", 
        "value": 0.0004465962476598543
    }, 
    "H1": {
        "error": 0.005765225173365233, 
        "filter_outliers_dict": {
            "filter_outliers": true, 
            "iterations": 1, 
            "std_devs": 2
        }, 
        "fit": "average", 
        "value": 0.018760165669342892
    }, 
    "H2": {
        "error": 0.008472872172096165, 
        "filter_outliers_dict": {
            "filter_outliers": true, 
            "iterations": 1, 
            "std_devs": 2
        }, 
        "fit": "average", 
        "value": -0.19223604402085268
    }, 
    "L1": {
        "error": 0.003000760037783964, 
        "filter_outliers_dict": {
            "filter_outliers": true, 
            "iterations": 1, 
            "std_devs": 2
        }, 
        "fit": "average", 
        "value": -0.024304368982059878
    }, 
    "L2": {
        "error": 0.006674930590558421, 
        "filter_outliers_dict": {
            "filter_outliers": true, 
            "iterations": 1, 
            "std_devs": 2
        }, 
        "fit": "average", 
        "value": -0.029355205905292163
    }
}