{
    "AX": {
        "error": 0.008347550157490446, 
        "filter_outliers_dict": {
            "filter_outliers": true, 
            "iterations": 1, 
            "std_devs": 2
        }, 
        "fit": "average", 
        "value": -0.09872041065744917
    }, 
    "CDD": {
        "error": 3.313652682696908e-05, 
        "filter_outliers_dict": {
            "filter_outliers": true, 
            "iterations": 1, 
            "std_devs": 10
        }, 
        "fit": "average", 
        "value": 0.0004614827881174953
    }, 
    "H1": {
        "error": 0.006810413105327915, 
        "filter_outliers_dict": {
            "filter_outliers": true, 
            "iterations": 1, 
            "std_devs": 2
        }, 
        "fit": "average", 
        "value": 0.005312009376135525
    }, 
    "H2": {
        "error": 0.00737748616603608, 
        "filter_outliers_dict": {
            "filter_outliers": true, 
            "iterations": 1, 
            "std_devs": 2
        }, 
        "fit": "average", 
        "value": -0.206545378341565
    }, 
    "L1": {
        "error": 0.003925685229547099, 
        "filter_outliers_dict": {
            "filter_outliers": true, 
            "iterations": 1, 
            "std_devs": 2
        }, 
        "fit": "average", 
        "value": -0.024999178414185266
    }, 
    "L2": {
        "error": 0.006319997251996178, 
        "filter_outliers_dict": {
            "filter_outliers": true, 
            "iterations": 1, 
            "std_devs": 2
        }, 
        "fit": "average", 
        "value": -0.024669531351435965
    }
}