{
    "Ar36": {
        "error": 0.0004445632435461109, 
        "filter_outliers_dict": {
            "filter_outliers": true, 
            "iterations": 1, 
            "std_devs": 2
        }, 
        "fit": "Linear", 
        "value": 0.03162053744036304
    }, 
    "Ar37": {
        "error": 0.010270944314254538, 
        "filter_outliers_dict": {
            "filter_outliers": true, 
            "iterations": 1, 
            "std_devs": 2
        }, 
        "fit": "linear", 
        "value": 0.5291476388318055
    }, 
    "Ar38": {
        "error": 0.005092776347645169, 
        "filter_outliers_dict": {
            "filter_outliers": true, 
            "iterations": 1, 
            "std_devs": 2
        }, 
        "fit": "linear", 
        "value": 3.1806328825413455
    }, 
    "Ar39": {
        "error": 0.030104475146815093, 
        "filter_outliers_dict": {
            "filter_outliers": true, 
            "iterations": 1, 
            "std_devs": 2
        }, 
        "fit": "Linear", 
        "value": 246.88673322776413
    }, 
    "Ar40": {
        "error": 0.08088654487123687, 
        "filter_outliers_dict": {
            "filter_outliers": true, 
            "iterations": 1, 
            "std_devs": 2
        }, 
        "fit": "Linear", 
        "value": 2066.9646070803005
    }, 
    "PM41": {
        "error": 0.07054034639202854, 
        "filter_outliers_dict": {
            "filter_outliers": false, 
            "iterations": 1, 
            "std_devs": 2
        }, 
        "fit": "linear", 
        "value": -0.0453151337726276
    }
}