{
    "Ar40AX": {
        "error": 0.007186192561846953, 
        "fit": "previous", 
        "references": [
            {
                "exclude": false, 
                "record_id": "ba-01-J-2295"
            }
        ], 
        "value": 0.09919311160381872
    }, 
    "Ar40H1": {
        "error": 0.007186192561846953, 
        "fit": "previous", 
        "references": [
            {
                "exclude": false, 
                "record_id": "ba-01-J-2295"
            }
        ], 
        "value": 0.09919311160381872
    }, 
    "Ar40L2": {
        "error": 0.007186192561846953, 
        "fit": "previous", 
        "references": [
            {
                "exclude": false, 
                "record_id": "ba-01-J-2295"
            }
        ], 
        "value": 0.09919311160381872
    }
}