{
    "Ar36": {
        "error": 0.0004142132258817393, 
        "filter_outliers_dict": {
            "filter_outliers": true, 
            "iterations": 1, 
            "std_devs": 2
        }, 
        "fit": "Linear", 
        "value": 0.027755208444793657
    }, 
    "Ar37": {
        "error": 0.009062880240583717, 
        "filter_outliers_dict": {
            "filter_outliers": true, 
            "iterations": 1, 
            "std_devs": 2
        }, 
        "fit": "linear", 
        "value": 0.015949204192853495
    }, 
    "Ar38": {
        "error": 0.004868071690211276, 
        "filter_outliers_dict": {
            "filter_outliers": true, 
            "iterations": 1, 
            "std_devs": 2
        }, 
        "fit": "linear", 
        "value": 0.8410207579831885
    }, 
    "Ar39": {
        "error": 0.016933904576760233, 
        "filter_outliers_dict": {
            "filter_outliers": true, 
            "iterations": 1, 
            "std_devs": 2
        }, 
        "fit": "Linear", 
        "value": 64.83563577454711
    }, 
    "Ar40": {
        "error": 0.04933995954832727, 
        "filter_outliers_dict": {
            "filter_outliers": true, 
            "iterations": 1, 
            "std_devs": 2
        }, 
        "fit": "Linear", 
        "value": 805.2661495996545
    }, 
    "PM41": {
        "error": 0.07297067529461106, 
        "filter_outliers_dict": {
            "filter_outliers": false, 
            "iterations": 1, 
            "std_devs": 2
        }, 
        "fit": "linear", 
        "value": -0.10919267124572268
    }
}