{
    "Ar36": {
        "error": 0.000310551325006072, 
        "filter_outliers_dict": {
            "filter_outliers": true, 
            "iterations": 1, 
            "std_devs": 2
        }, 
        "fit": "Parabolic", 
        "value": 0.024916003766329974
    }, 
    "Ar37": {
        "error": 0.0054222777766044965, 
        "filter_outliers_dict": {
            "filter_outliers": true, 
            "iterations": 1, 
            "std_devs": 2
        }, 
        "fit": "linear", 
        "value": 0.028031623483995426
    }, 
    "Ar38": {
        "error": 0.0020997583408089164, 
        "filter_outliers_dict": {
            "filter_outliers": true, 
            "iterations": 1, 
            "std_devs": 2
        }, 
        "fit": "linear", 
        "value": -0.015091064384946016
    }, 
    "Ar39": {
        "error": 0.009961690373218854, 
        "filter_outliers_dict": {
            "filter_outliers": true, 
            "iterations": 1, 
            "std_devs": 2
        }, 
        "fit": "Parabolic", 
        "value": -0.04825036334989132
    }, 
    "Ar40": {
        "error": 0.00738662638490146, 
        "filter_outliers_dict": {
            "filter_outliers": true, 
            "iterations": 1, 
            "std_devs": 2
        }, 
        "fit": "Parabolic", 
        "value": 5.672516851119075
    }, 
    "PM41": {
        "error": 0.0650765131621824, 
        "filter_outliers_dict": {
            "filter_outliers": false, 
            "iterations": 1, 
            "std_devs": 2
        }, 
        "fit": "linear", 
        "value": -0.16680470945130788
    }
}