{
    "AX": {
        "error": 0.004646091282742654, 
        "filter_outliers_dict": {
            "filter_outliers": true, 
            "iterations": 1, 
            "std_devs": 2
        }, 
        "fit": "average", 
        "value": -0.08071844450605352
    }, 
    "CDD": {
        "error": 3.198359786762766e-06, 
        "filter_outliers_dict": {
            "filter_outliers": true, 
            "iterations": 1, 
            "std_devs": 10
        }, 
        "fit": "average", 
        "value": 8.683815653428826e-06
    }, 
    "H1": {
        "error": 0.003694441745278125, 
        "filter_outliers_dict": {
            "filter_outliers": true, 
            "iterations": 1, 
            "std_devs": 2
        }, 
        "fit": "average", 
        "value": -0.028521117325913458
    }, 
    "H2": {
        "error": 0.004678719239914305, 
        "filter_outliers_dict": {
            "filter_outliers": true, 
            "iterations": 1, 
            "std_devs": 2
        }, 
        "fit": "average", 
        "value": -0.20311259691725883
    }, 
    "L1": {
        "error": 0.0021199330163712304, 
        "filter_outliers_dict": {
            "filter_outliers": true, 
            "iterations": 1, 
            "std_devs": 2
        }, 
        "fit": "average", 
        "value": -0.02116670525584948
    }, 
    "L2": {
        "error": 0.004695771338105803, 
        "filter_outliers_dict": {
            "filter_outliers": true, 
            "iterations": 1, 
            "std_devs": 2
        }, 
        "fit": "average", 
        "value": -0.028213632808110574
    }
}