{
    "AX": {
        "error": 0.007681798704966875, 
        "filter_outliers_dict": {
            "filter_outliers": true, 
            "iterations": 1, 
            "std_devs": 2
        }, 
        "fit": "average", 
        "value": -0.09063252437720812
    }, 
    "CDD": {
        "error": 3.0457332818667076e-05, 
        "filter_outliers_dict": {
            "filter_outliers": true, 
            "iterations": 1, 
            "std_devs": 10
        }, 
        "fit": "average", 
        "value": 0.00038953116882288133
    }, 
    "H1": {
        "error": 0.006194536170724643, 
        "filter_outliers_dict": {
            "filter_outliers": true, 
            "iterations": 1, 
            "std_devs": 2
        }, 
        "fit": "average", 
        "value": 0.009315346508695569
    }, 
    "H2": {
        "error": 0.007212804520682254, 
        "filter_outliers_dict": {
            "filter_outliers": true, 
            "iterations": 1, 
            "std_devs": 2
        }, 
        "fit": "average", 
        "value": -0.18863782209537816
    }, 
    "L1": {
        "error": 0.0029734052889230367, 
        "filter_outliers_dict": {
            "filter_outliers": true, 
            "iterations": 1, 
            "std_devs": 2
        }, 
        "fit": "average", 
        "value": -0.024942861050923255
    }, 
    "L2": {
        "error": 0.006341594639803932, 
        "filter_outliers_dict": {
            "filter_outliers": true, 
            "iterations": 1, 
            "std_devs": 2
        }, 
        "fit": "average", 
        "value": -0.03141983130262024
    }
}