{
    "AX": {
        "error": 0.00680104754000938, 
        "filter_outliers_dict": {
            "filter_outliers": true, 
            "iterations": 1, 
            "std_devs": 2
        }, 
        "fit": "average", 
        "value": -0.08407008388921969
    }, 
    "CDD": {
        "error": 2.186950032465487e-05, 
        "filter_outliers_dict": {
            "filter_outliers": true, 
            "iterations": 1, 
            "std_devs": 10
        }, 
        "fit": "average", 
        "value": 0.00023818466109326277
    }, 
    "H1": {
        "error": 0.004503326762498093, 
        "filter_outliers_dict": {
            "filter_outliers": true, 
            "iterations": 1, 
            "std_devs": 2
        }, 
        "fit": "average", 
        "value": -0.013566348766773016
    }, 
    "H2": {
        "error": 0.0067445609420478175, 
        "filter_outliers_dict": {
            "filter_outliers": true, 
            "iterations": 1, 
            "std_devs": 2
        }, 
        "fit": "average", 
        "value": -0.1766575294490186
    }, 
    "L1": {
        "error": 0.002829080583703376, 
        "filter_outliers_dict": {
            "filter_outliers": true, 
            "iterations": 1, 
            "std_devs": 2
        }, 
        "fit": "average", 
        "value": -0.02186304933267484
    }, 
    "L2": {
        "error": 0.0055746094871742405, 
        "filter_outliers_dict": {
            "filter_outliers": true, 
            "iterations": 1, 
            "std_devs": 2
        }, 
        "fit": "average", 
        "value": -0.0207111675717451
    }
}